orca_nw_lib/__init__.py
orca_nw_lib/bgp.py
orca_nw_lib/bgp_db.py
orca_nw_lib/bgp_gnmi.py
orca_nw_lib/bgp_influxdb.py
orca_nw_lib/bgp_rest.py
orca_nw_lib/common.py
orca_nw_lib/constants.py
orca_nw_lib/crm_influxdb.py
orca_nw_lib/crm_promdb.py
orca_nw_lib/device.py
orca_nw_lib/device_db.py
orca_nw_lib/device_gnmi.py
orca_nw_lib/device_info_influxdb.py
orca_nw_lib/device_info_promdb.py
orca_nw_lib/discovery.py
orca_nw_lib/dom_gnmi.py
orca_nw_lib/dom_influxdb.py
orca_nw_lib/dom_promdb.py
orca_nw_lib/evpn.py
orca_nw_lib/evpn_gnmi.py
orca_nw_lib/evpn_influxdb.py
orca_nw_lib/evpn_rest.py
orca_nw_lib/generate_code.py
orca_nw_lib/github/com/openconfig/gnmi/proto/gnmi_ext/gnmi_ext_pb2.py
orca_nw_lib/github/com/openconfig/gnmi/proto/gnmi_ext/gnmi_ext_pb2.pyi
orca_nw_lib/github.com/openconfig/gnmi/proto/gnmi_ext/gnmi_ext_pb2_grpc.py
orca_nw_lib/gnmi_pb2.py
orca_nw_lib/gnmi_pb2.pyi
orca_nw_lib/gnmi_pb2_grpc.py
orca_nw_lib/gnmi_sub.py
orca_nw_lib/gnmi_util.py
orca_nw_lib/graph_db_models.py
orca_nw_lib/influxdb_utils.py
orca_nw_lib/interface.py
orca_nw_lib/interface_db.py
orca_nw_lib/interface_gnmi.py
orca_nw_lib/interface_influxdb.py
orca_nw_lib/interface_promdb.py
orca_nw_lib/lldp.py
orca_nw_lib/lldp_db.py
orca_nw_lib/lldp_gnmi.py
orca_nw_lib/mclag.py
orca_nw_lib/mclag_db.py
orca_nw_lib/mclag_gnmi.py
orca_nw_lib/mclag_influxdb.py
orca_nw_lib/mclag_promdb.py
orca_nw_lib/orca_exceptions.py
orca_nw_lib/orca_nw_lib.yml
orca_nw_lib/orca_nw_lib_logging.yml
orca_nw_lib/platform.py
orca_nw_lib/platform_gnmi.py
orca_nw_lib/platform_influxdb.py
orca_nw_lib/port_chnl.py
orca_nw_lib/port_chnl_db.py
orca_nw_lib/port_chnl_gnmi.py
orca_nw_lib/portgroup.py
orca_nw_lib/portgroup_db.py
orca_nw_lib/portgroup_gnmi.py
orca_nw_lib/promdb_utils.py
orca_nw_lib/rest_client.py
orca_nw_lib/sag.py
orca_nw_lib/sag_gnmi.py
orca_nw_lib/sag_influxdb.py
orca_nw_lib/sag_promdb.py
orca_nw_lib/setup.py
orca_nw_lib/stp.py
orca_nw_lib/stp_db.py
orca_nw_lib/stp_gnmi.py
orca_nw_lib/stp_port.py
orca_nw_lib-1.3.63.dist-info/LICENSE
orca_nw_lib-1.3.63.dist-info/METADATA
orca_nw_lib-1.3.63.dist-info/WHEEL
orca_nw_lib-1.3.63.dist-info/RECORD
