Metadata-Version: 2.3
Name: orca_nw_lib
Version: 1.3.63
Summary: APIs to interact with SONiC NW
Author: Kamal Krishna Bhatt
Author-email: kamal.bhatt@stordis.com
Requires-Python: >=3.12,<4.0
Classifier: Programming Language :: Python :: 3
Classifier: Programming Language :: Python :: 3.12
Classifier: Programming Language :: Python :: 3.13
Requires-Dist: GitPython (>=3.1.37,<4.0.0)
Requires-Dist: PyYAML (>=6.0,<7.0)
Requires-Dist: black (>=24.10.0,<25.0.0)
Requires-Dist: grpcio-tools (>=1.69.0,<2.0.0)
Requires-Dist: influxdb-client (>=1.47.0,<2.0.0)
Requires-Dist: neo4j (>=5.4.0,<6.0.0)
Requires-Dist: neomodel (>=5.0.0,<6.0.0)
Requires-Dist: paramiko (>=3.5.0,<4.0.0)
Requires-Dist: prometheus-client (>=0.21.0,<0.22.0)
Requires-Dist: pyangbind (>=0.8.6,<0.9.0)
Requires-Dist: pytest (>=8.3.4,<9.0.0)
Requires-Dist: requests (>=2.28.2,<3.0.0)
Requires-Dist: wget (>=3.2,<4.0)
